jira_test_reporting/test_results_processor.py
jira_test_reporting/test_results_to_jira.py
jira_test_reporting/test_results_to_slack.py
jira_test_reporting-1.2.8.dist-info/licenses/LICENSE
jira_test_reporting-1.2.8.dist-info/METADATA
jira_test_reporting-1.2.8.dist-info/WHEEL
jira_test_reporting-1.2.8.dist-info/entry_points.txt
jira_test_reporting-1.2.8.dist-info/top_level.txt
jira_test_reporting-1.2.8.dist-info/RECORD
