Metadata-Version: 2.4
Name: jira_test_reporting
Version: 1.2.8
Summary: A utility to report pytest results to Jira and Slack
Author-email: Saurabh Patwardhan <patwardhansaurabhs@gmail.com>
Project-URL: Source, https://github.com/sspatwardhan/jira-test-reporting
Project-URL: Issues, https://github.com/sspatwardhan/jira-test-reporting/issues
Project-URL: Contribute, https://github.com/sspatwardhan/jira-test-reporting/blob/main/CONTRIBUTE.md
Classifier: Programming Language :: Python :: 3
Classifier: Operating System :: OS Independent
Requires-Python: >=3.12
License-File: LICENSE
Requires-Dist: requests>=2.32.3
Requires-Dist: configparser>=7.1.0
Requires-Dist: jira>=3.8.0
Dynamic: license-file
